sqlacodegen/__init__.py
sqlacodegen/codegen.py
sqlacodegen/main.py
sqlacodegen-2.3.0.post1.dist-info/LICENSE
sqlacodegen-2.3.0.post1.dist-info/METADATA
sqlacodegen-2.3.0.post1.dist-info/WHEEL
sqlacodegen-2.3.0.post1.dist-info/entry_points.txt
sqlacodegen-2.3.0.post1.dist-info/top_level.txt
sqlacodegen-2.3.0.post1.dist-info/RECORD
