Metadata-Version: 2.1
Name: sqlacodegen
Version: 2.3.0.post1
Summary: Automatic model code generator for SQLAlchemy
Author: Alex Grönholm
Author-email: alex.gronholm@nextday.fi
License: MIT
Project-URL: Bug Tracker, https://github.com/agronholm/sqlacodegen/issues
Project-URL: Source Code, https://github.com/agronholm/sqlacodegen
Keywords: sqlalchemy
Classifier: Development Status :: 5 - Production/Stable
Classifier: Intended Audience :: Developers
Classifier: License :: OSI Approved :: MIT License
Classifier: Environment :: Console
Classifier: Topic :: Database
Classifier: Topic :: Software Development :: Code Generators
Classifier: Programming Language :: Python
Classifier: Programming Language :: Python :: 2.7
Classifier: Programming Language :: Python :: 3
Classifier: Programming Language :: Python :: 3.5
Classifier: Programming Language :: Python :: 3.6
Classifier: Programming Language :: Python :: 3.7
Classifier: Programming Language :: Python :: 3.8
Requires-Python: !=3.0,!=3.1,!=3.2,!=3.3,!=3.4,>=2.7
Provides-Extra: test
License-File: LICENSE
